pypi/__init__.py
7asiba-0.1.dist-info/LICENSES.txt
7asiba-0.1.dist-info/METADATA
7asiba-0.1.dist-info/WHEEL
7asiba-0.1.dist-info/top_level.txt
7asiba-0.1.dist-info/RECORD
